{
  "url_name": "100201-silence-suzuka",
  "card_id": 100201,
  "char_id": 1002,
  "name_en": "Silence Suzuka",
  "name_jp": "サイレンススズカ",
  "name_ko": "사일런스 스즈카",
  "name_tw": "無聲鈴鹿",
  "title": "Silent Innocence",
  "title_jp": "[サイレントイノセンス]",
  "title_ko": "[사일런트 이노센스]",
  "title_tw": "[無聲純真]",
  "title_en_gl": "[Innocent Silence]",
  "rarity": 3,
  "costume": 100201,
  "release": "2021-02-24",
  "release_ko": "2022-06-20",
  "release_zh_tw": "2022-06-27",
  "release_en": "2025-06-26",
  "obtained": "gacha",
  "skills_unique": [
    100021
  ],
  "skills_innate": [
    200432,
    200552,
    200712
  ],
  "skills_evo": [
    {
      "old": 200431,
      "new": 100201111
    },
    {
      "old": 200551,
      "new": 100201211
    }
  ],
  "skills_awakening": [
    200022,
    200431,
    200542,
    200551
  ],
  "skills_event": [
    200022,
    202051,
    200532
  ],
  "stat_bonus": [
    20,
    0,
    0,
    10,
    0
  ],
  "talent_group": 100201,
  "base_stats": [
    101,
    84,
    77,
    100,
    88
  ],
  "aptitude": [
    "A",
    "G",
    "D",
    "A",
    "A",
    "E",
    "A",
    "C",
    "E",
    "G"
  ],
  "four_star_stats": [
    112,
    93,
    85,
    111,
    99
  ],
  "five_star_stats": [
    124,
    102,
    94,
    122,
    108
  ],
  "profile": {
    "self_intro": "I'm Silence Suzuka. I love to run, and I won't give up my lead to anyone. Uh... that's about it.",
    "tagline": "The silent runner aiming to break the sound barrier.",
    "weight": "No change",
    "shoes": "Left: 23.5cm Right: 23.0cm",
    "dorm": "Ritto Dormitory",
    "class": "Senior Division",
    "ears": "Sometimes doesn't hear anything when she thinks about running",
    "tail": "She always makes efforts to reduce her wind resistance",
    "strong": "Running long distances",
    "weak": "Crowded places",
    "family": "Gave her more pocket money for shoes",
    "secrets": [
      "Did you know? She's skilled at spinning pens."
    ]
  },
  "charData": {
    "url_name": "silence-suzuka",
    "char_id": 1002,
    "jp_name": "サイレンススズカ",
    "en_name": "Silence Suzuka",
    "name_ko": "사일런스 스즈카",
    "name_tw": "無聲鈴鹿",
    "playable": true,
    "playable_ko": true,
    "playable_zh_tw": true,
    "playable_en": true,
    "active": true,
    "active_ko": true,
    "active_zh_tw": true,
    "active_en": true,
    "va_en": "Marika Kouno",
    "va_ja": "高野麻里佳",
    "va_ko": "코노 마리카",
    "va_zh_tw": "高野麻里佳",
    "va_link": "https://myanimelist.net/people/35441/Marika_Kouno",
    "three_sizes": {
      "b": 70,
      "w": 53,
      "h": 79
    },
    "birth_day": 1,
    "birth_month": 5,
    "birth_year": 1994,
    "height": 161,
    "sex": 1,
    "race": "uma",
    "rl": {
      "country": "jp",
      "death": "1998-11-01",
      "races": 16,
      "wins": 9,
      "record": "9-1-0-6",
      "earnings": 455980000,
      "earnings_other": [
        [
          231000,
          "HKD"
        ]
      ],
      "active": "1997-1998"
    }
  },
  "__file": "100201-silence-suzuka.json",
  "has_release_en": true,
  "has_version": false,
  "profile_id": {
    "self_intro": "Aku Silence Suzuka. Aku suka berlari, dan aku tak akan menyerahkan posisi depanku pada siapa pun. Uh... itu saja sih.",
    "tagline": "Pelari sunyi yang bercita-cita menembus batas suara.",
    "weight": "Tidak berubah",
    "shoes": "Kiri : 23,5cm Kanan : 23,0cm",
    "dorm": "Asrama Ritto",
    "class": "Divisi Senior",
    "ears": "Kadang tak mendengar apa pun saat sedang memikirkan tentang berlari.",
    "tail": "Ia selalu berusaha mengurangi hambatan angin dengan ekornya.",
    "strong": "Lari jarak jauh",
    "weak": "Tempat ramai.",
    "family": "Memberinya uang jajan tambahan khusus untuk beli sepatu.",
    "secrets": [
      "Tahukah kamu? Dia jago memutar-mutar pena di jarinya."
    ]
  },
  "title_id": "Silent Innocence"
}